{
  "nodes": {
    "0": {
      "x": 24,
      "y": 18,
      "twist": 0
    },
    "1": {
      "x": -1,
      "y": 0,
      "twist": 0
    },
    "2": {
      "x": 4,
      "y": -2,
      "twist": 0
    },
    "3": {
      "x": 6,
      "y": 0,
      "twist": 0
    },
    "4": {
      "x": 4,
      "y": 2,
      "twist": 0
    },
    "5": {
      "x": 0,
      "y": 6,
      "twist": 0
    },
    "6": {
      "x": 12,
      "y": 6,
      "twist": 0
    },
    "7": {
      "x": 20,
      "y": 10,
      "twist": 0
    },
    "8": {
      "x": 18,
      "y": 12,
      "twist": 0
    },
    "9": {
      "x": 25,
      "y": 12,
      "twist": 0
    },
    "10": {
      "x": 20,
      "y": 14,
      "twist": 0
    },
    "11": {
      "x": 12,
      "y": 18,
      "twist": 0
    }
  },
  "paths": [
    {
      "path": [
        1,
        4,
        6,
        7,
        9,
        0,
        1
      ],
      "shifts": [
        {
          "from": 0,
          "to": 1,
          "dx": 24.0,
          "dy": 24.0
        }
      ]
    },
    {
      "path": [
        2,
        1,
        5,
        9,
        10,
        11,
        2
      ],
      "shifts": [
        {
          "from": 5,
          "to": 9,
          "dx": -24.0,
          "dy": 0.0
        },
        {
          "from": 11,
          "to": 2,
          "dx": 0.0,
          "dy": 24.0
        }
      ]
    },
    {
      "path": [
        2,
        3,
        6,
        8,
        10,
        0,
        2
      ],
      "shifts": [
        {
          "from": 0,
          "to": 2,
          "dx": 24.0,
          "dy": 24.0
        }
      ]
    },
    {
      "path": [
        3,
        4,
        5,
        7,
        8,
        11,
        3
      ],
      "shifts": [
        {
          "from": 5,
          "to": 7,
          "dx": -24.0,
          "dy": 0.0
        },
        {
          "from": 11,
          "to": 3,
          "dx": 0.0,
          "dy": 24.0
        }
      ]
    }
  ],
  "unit_yarns": {
    "0": {
      "path_id": 0,
      "starting_node": 1,
      "start_path_index": 0,
      "z_sign": -1,
      "z_height": 0.5,
      "name": 1,
      "repetitions": [
        {
          "count": 25,
          "dx": 24.0,
          "dy": 24.0
        },
        {
          "count": 25,
          "dx": 24.0,
          "dy": 0.0
        }
      ]
    },
    "1": {
      "path_id": 1,
      "starting_node": 2,
      "start_path_index": 0,
      "z_sign": -1,
      "z_height": 0.5,
      "name": 2,
      "repetitions": [
        {
          "count": 25,
          "dx": -24.0,
          "dy": 24.0
        },
        {
          "count": 25,
          "dx": 24.0,
          "dy": 0.0
        }
      ]
    },
    "2": {
      "path_id": 2,
      "starting_node": 2,
      "start_path_index": 0,
      "z_sign": 1,
      "z_height": 0.5,
      "name": 3,
      "repetitions": [
        {
          "count": 25,
          "dx": 24.0,
          "dy": 24.0
        },
        {
          "count": 25,
          "dx": 24.0,
          "dy": 0.0
        }
      ]
    },
    "3": {
      "path_id": 3,
      "starting_node": 3,
      "start_path_index": 0,
      "z_sign": 1,
      "z_height": 0.5,
      "name": 4,
      "repetitions": [
        {
          "count": 25,
          "dx": -24.0,
          "dy": 24.0
        },
        {
          "count": 25,
          "dx": 24.0,
          "dy": 0.0
        }
      ]
    }
  },
  "roi_bounds": {
    "x_min": 132.0,
    "x_max": 270.0,
    "y_min": 2.0,
    "y_max": 140.0,
    "z_min": -4.0,
    "z_max": 4.0
  }
}